{
	"folders": {},
	"connections": {
		"mysql8-17dc694b1e5-670935b765f3cd07": {
			"provider": "mysql",
			"driver": "mysql8",
			"name": "spring_foodmarket",
			"save-password": true,
			"read-only": false,
			"configuration": {
				"host": "localhost",
				"port": "3306",
				"database": "spring_foodmarket",
				"url": "jdbc:mysql://localhost:3306/spring_foodmarket",
				"home": "C:\\Program Files\\MySQL\\MySQL Router 8.0",
				"type": "dev",
				"properties": {
					"connectTimeout": "20000",
					"rewriteBatchedStatements": "true",
					"enabledTLSProtocols": "TLSv1,TLSv1.1,TLSv1.2",
					"allowPublicKeyRetrieval": "TRUE"
				},
				"auth-model": "native",
				"handlers": {}
			}
		}
	},
	"connection-types": {
		"dev": {
			"name": "Development",
			"color": "255,255,255",
			"description": "Regular development database",
			"auto-commit": true,
			"confirm-execute": false,
			"confirm-data-change": false,
			"auto-close-transactions": false
		}
	}
}